codeproject_ai_sdk/__init__.py
codeproject_ai_sdk/common.py
codeproject_ai_sdk/module_logging.py
codeproject_ai_sdk/module_options.py
codeproject_ai_sdk/module_runner.py
codeproject_ai_sdk/request_data.py
codeproject_ai_sdk/system_info.py
codeproject_ai_sdk/utils/__init__.py
codeproject_ai_sdk/utils/cpuinfo.py
codeproject_ai_sdk/utils/environment_check.py
codeproject_ai_sdk/utils/image_utils.py
codeproject_ai_sdk-0.0.21.dist-info/METADATA
codeproject_ai_sdk-0.0.21.dist-info/WHEEL
codeproject_ai_sdk-0.0.21.dist-info/top_level.txt
codeproject_ai_sdk-0.0.21.dist-info/RECORD
