Metadata-Version: 2.1
Name: codeproject-ai-sdk
Version: 0.0.21
Summary: Python SDK for writing Modules for CodeProject AI Server
Author: Chris Maunder, Matthew Dennis
License: SSPL
Classifier: Programming Language :: Python :: 3
Classifier: Programming Language :: Python :: 3.7
Classifier: Programming Language :: Python :: 3.8
Classifier: Programming Language :: Python :: 3.9
Classifier: Programming Language :: Python :: 3.10
Classifier: Programming Language :: Python :: 3.11
Classifier: Programming Language :: Python :: 3.12
Requires-Python: >=3.7
Requires-Dist: Pillow
Requires-Dist: charset-normalizer
Requires-Dist: commentjson
Requires-Dist: aiohttp
Requires-Dist: aiofiles
Requires-Dist: py-cpuinfo
Requires-Dist: requests
